fgo_api_types/__init__.py
fgo_api_types/base.py
fgo_api_types/basic.py
fgo_api_types/common.py
fgo_api_types/enums.py
fgo_api_types/gameenums.py
fgo_api_types/nice.py
fgo_api_types/raw.py
fgo_api_types/rayshift.py
fgo_api_types/search.py
fgo_api_types-2026.1.8.14.17.1.dist-info/METADATA
fgo_api_types-2026.1.8.14.17.1.dist-info/WHEEL
fgo_api_types-2026.1.8.14.17.1.dist-info/licenses/LICENSE
fgo_api_types-2026.1.8.14.17.1.dist-info/RECORD
