Metadata-Version: 2.4
Name: fgo-api-types
Version: 2026.1.8.14.17.1
Summary: Provide Pydantic types from FGO API
License-File: LICENSE
Author: squaresmile
Author-email: squaresmile@protonmail.com
Requires-Python: >=3.6,<4.0
Classifier: Programming Language :: Python :: 3
Classifier: Programming Language :: Python :: 3.6
Classifier: Programming Language :: Python :: 3.7
Classifier: Programming Language :: Python :: 3.8
Classifier: Programming Language :: Python :: 3.9
Classifier: Programming Language :: Python :: 3.10
Classifier: Programming Language :: Python :: 3.11
Classifier: Programming Language :: Python :: 3.12
Classifier: Programming Language :: Python :: 3.13
Classifier: Programming Language :: Python :: 3.14
Requires-Dist: pydantic (>=2,<3)
Project-URL: Homepage, https://api.atlasacademy.io
Project-URL: Repository, https://github.com/atlasacademy/fgo-game-data-api
